leaf_hello_world/__init__.py
leaf_hello_world/adapter.py
leaf_hello_world/device.json
leaf_hello_world/example.yaml
leaf_hello_world/interpreter.py
leaf_hello_world-0.1.0.dist-info/LICENSE
leaf_hello_world-0.1.0.dist-info/METADATA
leaf_hello_world-0.1.0.dist-info/WHEEL
leaf_hello_world-0.1.0.dist-info/entry_points.txt
leaf_hello_world-0.1.0.dist-info/RECORD
