Metadata-Version: 2.3
Name: leaf-hello-world
Version: 0.1.0
Summary: Leaf Adapter with a basic Hello World function. Creating a hello world message every x interval.
Author: Jasper Koehorst
Author-email: jasper.koehorst@wur.nl
Requires-Python: >=3.12,<4.0
Classifier: Programming Language :: Python :: 3
Classifier: Programming Language :: Python :: 3.12
Classifier: Programming Language :: Python :: 3.13
Requires-Dist: leaf-framework
